vanillapay/__init__.py
vanillapay/core.py
vanillapay/tools.py
vanillapay-1.0.1.dist-info/METADATA
vanillapay-1.0.1.dist-info/WHEEL
vanillapay-1.0.1.dist-info/top_level.txt
vanillapay-1.0.1.dist-info/RECORD
