Metadata-Version: 2.1
Name: vanillapay
Version: 1.0.1
Summary: This module offers a streamlined solution for seamlessly integrating the Vanilla Pay payment system into Python applications.
Author: Vanilla Pay Team
Project-URL: Homepage, https://github.com/Rohan29-AN/vanilla_pay_python
Keywords: vanilla pay,fintech,online_payment
Classifier: Programming Language :: Python :: 3.12
Classifier: License :: OSI Approved :: MIT License
Classifier: Operating System :: OS Independent
Requires-Python: >=3.12
Requires-Dist: python-dotenv
Requires-Dist: requests
